z_y_y_mcp_demo/__init__.py
z_y_y_mcp_demo-0.1.0.dist-info/METADATA
z_y_y_mcp_demo-0.1.0.dist-info/WHEEL
z_y_y_mcp_demo-0.1.0.dist-info/entry_points.txt
z_y_y_mcp_demo-0.1.0.dist-info/RECORD
