Metadata-Version: 2.4
Name: z-y-y-mcp-demo
Version: 0.1.0
Summary: Add your description here
Requires-Python: >=3.13
Requires-Dist: mcp[cli]>=1.9.4
